MP3/memory_quarter.sv
module memory_quarter #(
    parameter INIT_FILE = ""
)(
    input  logic       clk,
    input  logic [6:0] read_address, // 7-bit address (0 to 127)
    output logic [8:0] read_data     // 9-bit sample
);

    // Declare memory array for storing 128 9-bit samples of the first quarter cycle
    logic [8:0] sample_memory [0:127];

    // Load samples from INIT_FILE if provided
    initial if (INIT_FILE != "") begin
        $readmemh(INIT_FILE, sample_memory);
    end

    // Synchronous read from the memory array
    always_ff @(posedge clk) begin
        read_data <= sample_memory[read_address];
    end

endmodule

MP3/sine.sv
`include "memory_quarter.sv"

module top(
    input  logic clk,
    output logic _9b,    // D0
    output logic _6a,    // D1
    output logic _4a,    // D2
    output logic _2a,    // D3
    output logic _0a,    // D4
    output logic _5a,    // D5
    output logic _3b,    // D6
    output logic _49a,   // D7
    output logic _45a,   // D8
    output logic _48b    // D9
);

    // 9-bit counter for 512 sample positions (0 to 511)
    logic [8:0] counter = 0;
    always_ff @(posedge clk) begin
        counter <= counter + 1;
    end

    // Extract quarter selection bits and the lower 7 bits for addressing
    logic [1:0] quarter_sel;
    logic [6:0] counter_bits;
    assign quarter_sel = counter[8:7];
    assign counter_bits = counter[6:0];

    // Determine the quarter-wave memory address and compute the output data
    // We center the waveform around 512 (mid-scale for a 10-bit DAC) so that:
    // - In quarters 1 and 2 (positive half), data = 512 + quarter_data.
    // - In quarters 3 and 4 (negative half), data = 512 - quarter_data.
    logic [6:0] quarter_address;
    logic [9:0] data; // 10-bit output

    // Quarter-cycle memory outputs a 9-bit magnitude sample (0 to 511)
    logic [8:0] quarter_data;
    memory_quarter #(
        .INIT_FILE("sine_quarter.txt")
    ) u1 (
        .clk(clk),
        .read_address(quarter_address),
        .read_data(quarter_data)
    );

    // Use a case statement on quarter_sel to choose address ordering and compute data
    always_comb begin
        case (quarter_sel)
            2'b00: begin
                // Quarter 1: rising, direct order
                quarter_address = counter_bits;        // 0 to 127
                data = 10'd512 + quarter_data;           // Offset upward
            end
            2'b01: begin
                // Quarter 2: falling, reversed order
                quarter_address = 7'd127 - counter_bits; // Reverse order 127 down to 0
                data = 10'd512 + quarter_data;           // Still add for positive half
            end
            2'b10: begin
                // Quarter 3: falling, direct order
                quarter_address = counter_bits;          // 0 to 127
                data = 10'd512 - quarter_data;           // Subtract for negative half
            end
            2'b11: begin
                // Quarter 4: rising, reversed order
                quarter_address = 7'd127 - counter_bits; // Reverse order 127 down to 0
                data = 10'd512 - quarter_data;           // Subtract for negative half
            end
            default: begin
                quarter_address = 7'd0;
                data = 10'd512;
            end
        endcase
    end

    // Map the 10-bit data to DAC outputs in the specified order
    assign {_48b, _45a, _49a, _3b, _5a, _0a, _2a, _4a, _6a, _9b} = data;

endmodule

MP3/sine_tb.sv
`timescale 10ns/10ns
`include "sine.sv"

module tb_top;
    // Clock signal
    logic clk;

    // DAC output wires
    logic _9b;
    logic _6a;
    logic _4a;
    logic _2a;
    logic _0a;
    logic _5a;
    logic _3b;
    logic _49a;
    logic _45a;
    logic _48b;

    // Instantiate the top-level module
    top uut (
        .clk(clk),
        ._9b(_9b),
        ._6a(_6a),
        ._4a(_4a),
        ._2a(_2a),
        ._0a(_0a),
        ._5a(_5a),
        ._3b(_3b),
        ._49a(_49a),
        ._45a(_45a),
        ._48b(_48b)
    );

    // Generate a clock with a 10ns period (100MHz)
    initial begin
        clk = 0;
        forever #5 clk = ~clk;
    end

    // Dump waveforms and end simulation after a full cycle plus margin
    initial begin
        $dumpfile("tb_top.vcd");  // VCD file for viewing waveforms in gtkwave
        $dumpvars(0, tb_top);
        // Run simulation for 12000ns, which covers more than two full cycle (5120ns for one cycle)
        #12000;
        $finish;
    end
endmodule

MP3/tb_top.vcd
$date
	Tue Mar 11 23:56:44 2025
$end
$version
	Icarus Verilog
$end
$timescale
	10ns
$end
$scope module tb_top $end
$var wire 1 ! _9b $end
$var wire 1 " _6a $end
$var wire 1 # _5a $end
$var wire 1 $ _4a $end
$var wire 1 % _49a $end
$var wire 1 & _48b $end
$var wire 1 ' _45a $end
$var wire 1 ( _3b $end
$var wire 1 ) _2a $end
$var wire 1 * _0a $end
$var reg 1 + clk $end
$scope module uut $end
$var wire 1 + clk $end
$var wire 2 , quarter_sel [1:0] $end
$var wire 9 - quarter_data [8:0] $end
$var wire 7 . counter_bits [6:0] $end
$var wire 1 ! _9b $end
$var wire 1 " _6a $end
$var wire 1 # _5a $end
$var wire 1 $ _4a $end
$var wire 1 % _49a $end
$var wire 1 & _48b $end
$var wire 1 ' _45a $end
$var wire 1 ( _3b $end
$var wire 1 ) _2a $end
$var wire 1 * _0a $end
$var reg 9 / counter [8:0] $end
$var reg 10 0 data [9:0] $end
$var reg 7 1 quarter_address [6:0] $end
$scope module u1 $end
$var wire 1 + clk $end
$var wire 7 2 read_address [6:0] $end
$var parameter 128 3 INIT_FILE $end
$var reg 9 4 read_data [8:0] $end
$upscope $end
$upscope $end
$upscope $end
$enddefinitions $end
$comment Show the parameter values. $end
$dumpall
b1110011011010010110111001100101010111110111000101110101011000010111001001110100011001010111001000101110011101000111100001110100 3
$end
#0
$dumpvars
bx 4
b0 2
b0 1
bx 0
b0 /
b0 .
bx -
b0 ,
0+
x*
x)
x(
x'
x&
x%
x$
x#
x"
x!
$end
#5
1&
0'
0%
0(
0#
0*
0)
0$
0"
0!
b1000000000 0
b1 1
b1 2
b1 .
b0 -
b0 4
b1 /
1+
#10
0+
#15
b10 1
b10 2
1$
1"
b10 .
b1000000110 0
b10 /
b110 -
b110 4
1+
#20
0+
#25
1)
0"
1!
b1000001101 0
b11 1
b11 2
b11 .
b1101 -
b1101 4
b11 /
1+
#30
0+
#35
b100 1
b100 2
1*
0)
0$
1"
b100 .
b1000010011 0
b100 /
b10011 -
b10011 4
1+
#40
0+
#45
1)
0"
b1000011001 0
b101 1
b101 2
b101 .
b11001 -
b11001 4
b101 /
1+
#50
0+
#55
b110 1
b110 2
1#
0*
0)
0!
b110 .
b1000100000 0
b110 /
b100000 -
b100000 4
1+
#60
0+
#65
1$
1"
b1000100110 0
b111 1
b111 2
b111 .
b100110 -
b100110 4
b111 /
1+
#70
0+
#75
b1000 1
b1000 2
1)
0"
b1000 .
b1000101100 0
b1000 /
b101100 -
b101100 4
1+
#80
0+
#85
1*
0)
0$
1"
b1000110010 0
b1001 1
b1001 2
b1001 .
b110010 -
b110010 4
b1001 /
1+
#90
0+
#95
b1010 1
b1010 2
1)
0"
1!
b1010 .
b1000111001 0
b1010 /
b111001 -
b111001 4
1+
#100
0+
#105
1$
1"
b1000111111 0
b1011 1
b1011 2
b1011 .
b111111 -
b111111 4
b1011 /
1+
#110
0+
#115
b1100 1
b1100 2
1(
0#
0*
0)
0"
b1100 .
b1001000101 0
b1100 /
b1000101 -
b1000101 4
1+
#120
0+
#125
1)
0!
b1001001100 0
b1101 1
b1101 2
b1101 .
b1001100 -
b1001100 4
b1101 /
1+
#130
0+
#135
b1110 1
b1110 2
1*
0)
0$
1"
b1110 .
b1001010010 0
b1110 /
b1010010 -
b1010010 4
1+
#140
0+
#145
1)
0"
b1001011000 0
b1111 1
b1111 2
b1111 .
b1011000 -
b1011000 4
b1111 /
1+
#150
0+
#155
b10000 1
b10000 2
1$
1"
b10000 .
b1001011110 0
b10000 /
b1011110 -
b1011110 4
1+
#160
0+
#165
1#
0*
0)
0"
b1001100100 0
b10001 1
b10001 2
b10001 .
b1100100 -
b1100100 4
b10001 /
1+
#170
0+
#175
b10010 1
b10010 2
1)
0$
1"
1!
b10010 .
b1001101011 0
b10010 /
b1101011 -
b1101011 4
1+
#180
0+
#185
1*
0)
0"
b1001110001 0
b10011 1
b10011 2
b10011 .
b1110001 -
b1110001 4
b10011 /
1+
#190
0+
#195
b10100 1
b10100 2
1$
1"
b10100 .
b1001110111 0
b10100 /
b1110111 -
b1110111 4
1+
#200
0+
#205
1)
0"
b1001111101 0
b10101 1
b10101 2
b10101 .
b1111101 -
b1111101 4
b10101 /
1+
#210
0+
#215
b10110 1
b10110 2
1%
0(
0#
0*
0)
0$
1"
b10110 .
b1010000011 0
b10110 /
b10000011 -
b10000011 4
1+
#220
0+
#225
1)
0"
b1010001001 0
b10111 1
b10111 2
b10111 .
b10001001 -
b10001001 4
b10111 /
1+
#230
0+
#235
b11000 1
b11000 2
1$
1"
b11000 .
b1010001111 0
b11000 /
b10001111 -
b10001111 4
1+
#240
0+
#245
1*
0)
0"
b1010010101 0
b11001 1
b11001 2
b11001 .
b10010101 -
b10010101 4
b11001 /
1+
#250
0+
#255
b11010 1
b11010 2
1)
0!
b11010 .
b1010011100 0
b11010 /
b10011100 -
b10011100 4
1+
#260
0+
#265
1#
0*
0)
0$
1"
b1010100010 0
b11011 1
b11011 2
b11011 .
b10100010 -
b10100010 4
b11011 /
1+
#270
0+
#275
b11100 1
b11100 2
1$
1!
b11100 .
b1010100111 0
b11100 /
b10100111 -
b10100111 4
1+
#280
0+
#285
1)
0"
b1010101101 0
b11101 1
b11101 2
b11101 .
b10101101 -
b10101101 4
b11101 /
1+
#290
0+
#295
b11110 1
b11110 2
1*
0)
0$
1"
b11110 .
b1010110011 0
b11110 /
b10110011 -
b10110011 4
1+
#300
0+
#305
1)
0"
b1010111001 0
b11111 1
b11111 2
b11111 .
b10111001 -
b10111001 4
b11111 /
1+
#310
0+
#315
b100000 1
b100000 2
1$
1"
b100000 .
b1010111111 0
b100000 /
b10111111 -
b10111111 4
1+
#320
0+
#325
1(
0#
0*
0)
0"
b1011000101 0
b100001 1
b100001 2
b100001 .
b11000101 -
b11000101 4
b100001 /
1+
#330
0+
#335
b100010 1
b100010 2
1)
0$
1"
b100010 .
b1011001011 0
b100010 /
b11001011 -
b11001011 4
1+
#340
0+
#345
1*
0)
0"
b1011010001 0
b100011 1
b100011 2
b100011 .
b11010001 -
b11010001 4
b100011 /
1+
#350
0+
#355
b100100 1
b100100 2
1$
1"
0!
b100100 .
b1011010110 0
b100100 /
b11010110 -
b11010110 4
1+
#360
0+
#365
1)
0"
b1011011100 0
b100101 1
b100101 2
b100101 .
b11011100 -
b11011100 4
b100101 /
1+
#370
0+
#375
b100110 1
b100110 2
1#
0*
0)
0$
1"
b100110 .
b1011100010 0
b100110 /
b11100010 -
b11100010 4
1+
#380
0+
#385
1$
1!
b1011100111 0
b100111 1
b100111 2
b100111 .
b11100111 -
b11100111 4
b100111 /
1+
#390
0+
#395
b101000 1
b101000 2
1)
0"
b101000 .
b1011101101 0
b101000 /
b11101101 -
b11101101 4
1+
#400
0+
#405
1*
0)
0$
1"
b1011110011 0
b101001 1
b101001 2
b101001 .
b11110011 -
b11110011 4
b101001 /
1+
#410
0+
#415
b101010 1
b101010 2
1)
0"
0!
b101010 .
b1011111000 0
b101010 /
b11111000 -
b11111000 4
1+
#420
0+
#425
1$
1"
b1011111110 0
b101011 1
b101011 2
b101011 .
b11111110 -
b11111110 4
b101011 /
1+
#430
0+
#435
b101100 1
b101100 2
1'
0%
0(
0#
0*
0)
0$
1!
b101100 .
b1100000011 0
b101100 /
b100000011 -
b100000011 4
1+
#440
0+
#445
1)
0"
b1100001001 0
b101101 1
b101101 2
b101101 .
b100001001 -
b100001001 4
b101101 /
1+
#450
0+
#455
b101110 1
b101110 2
1$
1"
0!
b101110 .
b1100001110 0
b101110 /
b100001110 -
b100001110 4
1+
#460
0+
#465
1*
0)
0$
1!
b1100010011 0
b101111 1
b101111 2
b101111 .
b100010011 -
b100010011 4
b101111 /
1+
#470
0+
#475
b110000 1
b110000 2
1)
0"
b110000 .
b1100011001 0
b110000 /
b100011001 -
b100011001 4
1+
#480
0+
#485
1$
1"
0!
b1100011110 0
b110001 1
b110001 2
b110001 .
b100011110 -
b100011110 4
b110001 /
1+
#490
0+
#495
b110010 1
b110010 2
1#
0*
0)
0$
1!
b110010 .
b1100100011 0
b110010 /
b100100011 -
b100100011 4
1+
#500
0+
#505
1)
0"
0!
b1100101000 0
b110011 1
b110011 2
b110011 .
b100101000 -
b100101000 4
b110011 /
1+
#510
0+
#515
b110100 1
b110100 2
1$
1!
b110100 .
b1100101101 0
b110100 /
b100101101 -
b100101101 4
1+
#520
0+
#525
1*
0)
0$
1"
0!
b1100110010 0
b110101 1
b110101 2
b110101 .
b100110010 -
b100110010 4
b110101 /
1+
#530
0+
#535
b110110 1
b110110 2
1$
1!
b110110 .
b1100110111 0
b110110 /
b100110111 -
b100110111 4
1+
#540
0+
#545
1)
0"
0!
b1100111100 0
b110111 1
b110111 2
b110111 .
b100111100 -
b100111100 4
b110111 /
1+
#550
0+
#555
b111000 1
b111000 2
1(
0#
0*
0)
0$
1!
b111000 .
b1101000001 0
b111000 /
b101000001 -
b101000001 4
1+
#560
0+
#565
1$
1"
0!
b1101000110 0
b111001 1
b111001 2
b111001 .
b101000110 -
b101000110 4
b111001 /
1+
#570
0+
#575
b111010 1
b111010 2
1)
0$
1!
b111010 .
b1101001011 0
b111010 /
b101001011 -
b101001011 4
1+
#580
0+
#585
1*
0)
0"
0!
b1101010000 0
b111011 1
b111011 2
b111011 .
b101010000 -
b101010000 4
b111011 /
1+
#590
0+
#595
b111100 1
b111100 2
1$
1!
b111100 .
b1101010101 0
b111100 /
b101010101 -
b101010101 4
1+
#600
0+
#605
1)
0$
b1101011001 0
b111101 1
b111101 2
b111101 .
b101011001 -
b101011001 4
b111101 /
1+
#610
0+
#615
b111110 1
b111110 2
1$
1"
0!
b111110 .
b1101011110 0
b111110 /
b101011110 -
b101011110 4
1+
#620
0+
#625
1#
0*
0)
0$
1!
b1101100011 0
b111111 1
b111111 2
b111111 .
b101100011 -
b101100011 4
b111111 /
1+
#630
0+
#635
b1000000 1
b1000000 2
1$
b1000000 .
b1101100111 0
b1000000 /
b101100111 -
b101100111 4
1+
#640
0+
#645
1)
0"
0!
b1101101100 0
b1000001 1
b1000001 2
b1000001 .
b101101100 -
b101101100 4
b1000001 /
1+
#650
0+
#655
b1000010 1
b1000010 2
1*
0)
0$
b1000010 .
b1101110000 0
b1000010 /
b101110000 -
b101110000 4
1+
#660
0+
#665
1$
b1101110100 0
b1000011 1
b1000011 2
b1000011 .
b101110100 -
b101110100 4
b1000011 /
1+
#670
0+
#675
b1000100 1
b1000100 2
1)
0$
1!
b1000100 .
b1101111001 0
b1000100 /
b101111001 -
b101111001 4
1+
#680
0+
#685
1$
b1101111101 0
b1000101 1
b1000101 2
b1000101 .
b101111101 -
b101111101 4
b1000101 /
1+
#690
0+
#695
b1000110 1
b1000110 2
1%
0(
0#
0*
0)
0$
b1000110 .
b1110000001 0
b1000110 /
b110000001 -
b110000001 4
1+
#700
0+
#705
1$
b1110000101 0
b1000111 1
b1000111 2
b1000111 .
b110000101 -
b110000101 4
b1000111 /
1+
#710
0+
#715
b1001000 1
b1001000 2
1)
0$
b1001000 .
b1110001001 0
b1001000 /
b110001001 -
b110001001 4
1+
#720
0+
#725
1$
b1110001101 0
b1001001 1
b1001001 2
b1001001 .
b110001101 -
b110001101 4
b1001001 /
1+
#730
0+
#735
b1001010 1
b1001010 2
1*
0)
0$
b1001010 .
b1110010001 0
b1001010 /
b110010001 -
b110010001 4
1+
#740
0+
#745
1$
b1110010101 0
b1001011 1
b1001011 2
b1001011 .
b110010101 -
b110010101 4
b1001011 /
1+
#750
0+
#755
b1001100 1
b1001100 2
1)
0$
b1001100 .
b1110011001 0
b1001100 /
b110011001 -
b110011001 4
1+
#760
0+
#765
1$
b1110011101 0
b1001101 1
b1001101 2
b1001101 .
b110011101 -
b110011101 4
b1001101 /
1+
#770
0+
#775
b1001110 1
b1001110 2
1#
0*
0)
0$
0!
b1001110 .
b1110100000 0
b1001110 /
b110100000 -
b110100000 4
1+
#780
0+
#785
1$
b1110100100 0
b1001111 1
b1001111 2
b1001111 .
b110100100 -
b110100100 4
b1001111 /
1+
#790
0+
#795
b1010000 1
b1010000 2
1)
0$
b1010000 .
b1110101000 0
b1010000 /
b110101000 -
b110101000 4
1+
#800
0+
#805
1"
1!
b1110101011 0
b1010001 1
b1010001 2
b1010001 .
b110101011 -
b110101011 4
b1010001 /
1+
#810
0+
#815
b1010010 1
b1010010 2
1$
b1010010 .
b1110101111 0
b1010010 /
b110101111 -
b110101111 4
1+
#820
0+
#825
1*
0)
0$
0!
b1110110010 0
b1010011 1
b1010011 2
b1010011 .
b110110010 -
b110110010 4
b1010011 /
1+
#830
0+
#835
b1010100 1
b1010100 2
1$
0"
1!
b1010100 .
b1110110101 0
b1010100 /
b110110101 -
b110110101 4
1+
#840
0+
#845
1)
0$
0!
b1110111000 0
b1010101 1
b1010101 2
b1010101 .
b110111000 -
b110111000 4
b1010101 /
1+
#850
0+
#855
b1010110 1
b1010110 2
1$
b1010110 .
b1110111100 0
b1010110 /
b110111100 -
b110111100 4
1+
#860
0+
#865
1"
1!
b1110111111 0
b1010111 1
b1010111 2
b1010111 .
b110111111 -
b110111111 4
b1010111 /
1+
#870
0+
#875
b1011000 1
b1011000 2
1(
0#
0*
0)
0$
0!
b1011000 .
b1111000010 0
b1011000 /
b111000010 -
b111000010 4
1+
#880
0+
#885
1$
0"
1!
b1111000101 0
b1011001 1
b1011001 2
b1011001 .
b111000101 -
b111000101 4
b1011001 /
1+
#890
0+
#895
b1011010 1
b1011010 2
1)
0$
0!
b1011010 .
b1111001000 0
b1011010 /
b111001000 -
b111001000 4
1+
#900
0+
#905
1"
b1111001010 0
b1011011 1
b1011011 2
b1011011 .
b111001010 -
b111001010 4
b1011011 /
1+
#910
0+
#915
b1011100 1
b1011100 2
1$
0"
1!
b1011100 .
b1111001101 0
b1011100 /
b111001101 -
b111001101 4
1+
#920
0+
#925
1*
0)
0$
0!
b1111010000 0
b1011101 1
b1011101 2
b1011101 .
b111010000 -
b111010000 4
b1011101 /
1+
#930
0+
#935
b1011110 1
b1011110 2
1"
b1011110 .
b1111010010 0
b1011110 /
b111010010 -
b111010010 4
1+
#940
0+
#945
1$
0"
1!
b1111010101 0
b1011111 1
b1011111 2
b1011111 .
b111010101 -
b111010101 4
b1011111 /
1+
#950
0+
#955
b1100000 1
b1100000 2
1"
b1100000 .
b1111010111 0
b1100000 /
b111010111 -
b111010111 4
1+
#960
0+
#965
1)
0$
0!
b1111011010 0
b1100001 1
b1100001 2
b1100001 .
b111011010 -
b111011010 4
b1100001 /
1+
#970
0+
#975
b1100010 1
b1100010 2
1$
0"
b1100010 .
b1111011100 0
b1100010 /
b111011100 -
b111011100 4
1+
#980
0+
#985
1"
b1111011110 0
b1100011 1
b1100011 2
b1100011 .
b111011110 -
b111011110 4
b1100011 /
1+
#990
0+
#995
b1100100 1
b1100100 2
1#
0*
0)
0$
0"
1!
b1100100 .
b1111100001 0
b1100100 /
b111100001 -
b111100001 4
1+
#1000
0+
#1005
1"
b1111100011 0
b1100101 1
b1100101 2
b1100101 .
b111100011 -
b111100011 4
b1100101 /
1+
#1010
0+
#1015
b1100110 1
b1100110 2
1$
0"
b1100110 .
b1111100101 0
b1100110 /
b111100101 -
b111100101 4
1+
#1020
0+
#1025
1"
b1111100111 0
b1100111 1
b1100111 2
b1100111 .
b111100111 -
b111100111 4
b1100111 /
1+
#1030
0+
#1035
b1101000 1
b1101000 2
1)
0$
0"
b1101000 .
b1111101001 0
b1101000 /
b111101001 -
b111101001 4
1+
#1040
0+
#1045
1"
0!
b1111101010 0
b1101001 1
b1101001 2
b1101001 .
b111101010 -
b111101010 4
b1101001 /
1+
#1050
0+
#1055
b1101010 1
b1101010 2
1$
0"
b1101010 .
b1111101100 0
b1101010 /
b111101100 -
b111101100 4
1+
#1060
0+
#1065
1"
b1111101110 0
b1101011 1
b1101011 2
b1101011 .
b111101110 -
b111101110 4
b1101011 /
1+
#1070
0+
#1075
b1101100 1
b1101100 2
1!
b1101100 .
b1111101111 0
b1101100 /
b111101111 -
b111101111 4
1+
#1080
0+
#1085
1*
0)
0$
0"
b1111110001 0
b1101101 1
b1101101 2
b1101101 .
b111110001 -
b111110001 4
b1101101 /
1+
#1090
0+
#1095
b1101110 1
b1101110 2
1"
0!
b1101110 .
b1111110010 0
b1101110 /
b111110010 -
b111110010 4
1+
#1100
0+
#1105
1$
0"
b1111110100 0
b1101111 1
b1101111 2
b1101111 .
b111110100 -
b111110100 4
b1101111 /
1+
#1110
0+
#1115
b1110000 1
b1110000 2
1!
b1110000 .
b1111110101 0
b1110000 /
b111110101 -
b111110101 4
1+
#1120
0+
#1125
1"
0!
b1111110110 0
b1110001 1
b1110001 2
b1110001 .
b111110110 -
b111110110 4
b1110001 /
1+
#1130
0+
#1135
b1110010 1
b1110010 2
1!
b1110010 .
b1111110111 0
b1110010 /
b111110111 -
b111110111 4
1+
#1140
0+
#1145
1)
0$
0"
0!
b1111111000 0
b1110011 1
b1110011 2
b1110011 .
b111111000 -
b111111000 4
b1110011 /
1+
#1150
0+
#1155
b1110100 1
b1110100 2
1!
b1110100 .
b1111111001 0
b1110100 /
b111111001 -
b111111001 4
1+
#1160
0+
#1165
1"
0!
b1111111010 0
b1110101 1
b1110101 2
b1110101 .
b111111010 -
b111111010 4
b1110101 /
1+
#1170
0+
#1175
b1110110 1
b1110110 2
1!
b1110110 .
b1111111011 0
b1110110 /
b111111011 -
b111111011 4
1+
#1180
0+
#1185
1$
0"
0!
b1111111100 0
b1110111 1
b1110111 2
b1110111 .
b111111100 -
b111111100 4
b1110111 /
1+
#1190
0+
#1195
b1111000 1
b1111000 2
1!
b1111000 .
b1111111101 0
b1111000 /
b111111101 -
b111111101 4
1+
#1200
0+
#1205
b1111001 1
b1111001 2
b1111001 .
b1111001 /
1+
#1210
0+
#1215
b1111010 1
b1111010 2
1"
0!
b1111010 .
b1111111110 0
b1111010 /
b111111110 -
b111111110 4
1+
#1220
0+
#1225
b1111011 1
b1111011 2
b1111011 .
b1111011 /
1+
#1230
0+
#1235
b1111100 1
b1111100 2
b1111100 .
b1111100 /
1+
#1240
0+
#1245
1!
b1111111111 0
b1111101 1
b1111101 2
b1111101 .
b111111111 -
b111111111 4
b1111101 /
1+
#1250
0+
#1255
b1111110 1
b1111110 2
b1111110 .
b1111110 /
1+
#1260
0+
#1265
b1111111 1
b1111111 2
b1111111 .
b1111111 /
1+
#1270
0+
#1275
b1 ,
b0 .
b10000000 /
1+
#1280
0+
#1285
b1111110 1
b1111110 2
b1 .
b10000001 /
1+
#1290
0+
#1295
b1111101 1
b1111101 2
b10 .
b10000010 /
1+
#1300
0+
#1305
b1111100 1
b1111100 2
b11 .
b10000011 /
1+
#1310
0+
#1315
b1111011 1
b1111011 2
b100 .
b10000100 /
1+
#1320
0+
#1325
0!
b1111111110 0
b1111010 1
b1111010 2
b101 .
b111111110 -
b111111110 4
b10000101 /
1+
#1330
0+
#1335
b1111001 1
b1111001 2
b110 .
b10000110 /
1+
#1340
0+
#1345
b1111000 1
b1111000 2
b111 .
b10000111 /
1+
#1350
0+
#1355
b1110111 1
b1110111 2
0"
1!
b1000 .
b1111111101 0
b10001000 /
b111111101 -
b111111101 4
1+
#1360
0+
#1365
b1110110 1
b1110110 2
b1001 .
b10001001 /
1+
#1370
0+
#1375
b1110101 1
b1110101 2
0!
b1010 .
b1111111100 0
b10001010 /
b111111100 -
b111111100 4
1+
#1380
0+
#1385
0$
1"
1!
b1111111011 0
b1110100 1
b1110100 2
b1011 .
b111111011 -
b111111011 4
b10001011 /
1+
#1390
0+
#1395
b1110011 1
b1110011 2
0!
b1100 .
b1111111010 0
b10001100 /
b111111010 -
b111111010 4
1+
#1400
0+
#1405
0"
1!
b1111111001 0
b1110010 1
b1110010 2
b1101 .
b111111001 -
b111111001 4
b10001101 /
1+
#1410
0+
#1415
b1110001 1
b1110001 2
0!
b1110 .
b1111111000 0
b10001110 /
b111111000 -
b111111000 4
1+
#1420
0+
#1425
0)
1$
1"
1!
b1111110111 0
b1110000 1
b1110000 2
b1111 .
b111110111 -
b111110111 4
b10001111 /
1+
#1430
0+
#1435
b1101111 1
b1101111 2
0!
b10000 .
b1111110110 0
b10010000 /
b111110110 -
b111110110 4
1+
#1440
0+
#1445
0"
1!
b1111110101 0
b1101110 1
b1101110 2
b10001 .
b111110101 -
b111110101 4
b10010001 /
1+
#1450
0+
#1455
b1101101 1
b1101101 2
0!
b10010 .
b1111110100 0
b10010010 /
b111110100 -
b111110100 4
1+
#1460
0+
#1465
0$
1"
b1111110010 0
b1101100 1
b1101100 2
b10011 .
b111110010 -
b111110010 4
b10010011 /
1+
#1470
0+
#1475
b1101011 1
b1101011 2
0"
1!
b10100 .
b1111110001 0
b10010100 /
b111110001 -
b111110001 4
1+
#1480
0+
#1485
0*
1)
1$
1"
b1111101111 0
b1101010 1
b1101010 2
b10101 .
b111101111 -
b111101111 4
b10010101 /
1+
#1490
0+
#1495
b1101001 1
b1101001 2
0!
b10110 .
b1111101110 0
b10010110 /
b111101110 -
b111101110 4
1+
#1500
0+
#1505
0"
b1111101100 0
b1101000 1
b1101000 2
b10111 .
b111101100 -
b111101100 4
b10010111 /
1+
#1510
0+
#1515
b1100111 1
b1100111 2
0$
1"
b11000 .
b1111101010 0
b10011000 /
b111101010 -
b111101010 4
1+
#1520
0+
#1525
0"
1!
b1111101001 0
b1100110 1
b1100110 2
b11001 .
b111101001 -
b111101001 4
b10011001 /
1+
#1530
0+
#1535
b1100101 1
b1100101 2
0)
1$
1"
b11010 .
b1111100111 0
b10011010 /
b111100111 -
b111100111 4
1+
#1540
0+
#1545
0"
b1111100101 0
b1100100 1
b1100100 2
b11011 .
b111100101 -
b111100101 4
b10011011 /
1+
#1550
0+
#1555
b1100011 1
b1100011 2
0$
1"
b11100 .
b1111100011 0
b10011100 /
b111100011 -
b111100011 4
1+
#1560
0+
#1565
0"
b1111100001 0
b1100010 1
b1100010 2
b11101 .
b111100001 -
b111100001 4
b10011101 /
1+
#1570
0+
#1575
b1100001 1
b1100001 2
0#
1*
1)
1$
1"
0!
b11110 .
b1111011110 0
b10011110 /
b111011110 -
b111011110 4
1+
#1580
0+
#1585
0"
b1111011100 0
b1100000 1
b1100000 2
b11111 .
b111011100 -
b111011100 4
b10011111 /
1+
#1590
0+
#1595
b1011111 1
b1011111 2
0$
1"
b100000 .
b1111011010 0
b10100000 /
b111011010 -
b111011010 4
1+
#1600
0+
#1605
0)
1$
1!
b1111010111 0
b1011110 1
b1011110 2
b100001 .
b111010111 -
b111010111 4
b10100001 /
1+
#1610
0+
#1615
b1011101 1
b1011101 2
0"
b100010 .
b1111010101 0
b10100010 /
b111010101 -
b111010101 4
1+
#1620
0+
#1625
0$
1"
0!
b1111010010 0
b1011100 1
b1011100 2
b100011 .
b111010010 -
b111010010 4
b10100011 /
1+
#1630
0+
#1635
b1011011 1
b1011011 2
0"
b100100 .
b1111010000 0
b10100100 /
b111010000 -
b111010000 4
1+
#1640
0+
#1645
0*
1)
1$
1!
b1111001101 0
b1011010 1
b1011010 2
b100101 .
b111001101 -
b111001101 4
b10100101 /
1+
#1650
0+
#1655
b1011001 1
b1011001 2
0$
1"
0!
b100110 .
b1111001010 0
b10100110 /
b111001010 -
b111001010 4
1+
#1660
0+
#1665
0"
b1111001000 0
b1011000 1
b1011000 2
b100111 .
b111001000 -
b111001000 4
b10100111 /
1+
#1670
0+
#1675
b1010111 1
b1010111 2
0)
1$
1!
b101000 .
b1111000101 0
b10101000 /
b111000101 -
b111000101 4
1+
#1680
0+
#1685
0$
1"
0!
b1111000010 0
b1010110 1
b1010110 2
b101001 .
b111000010 -
b111000010 4
b10101001 /
1+
#1690
0+
#1695
b1010101 1
b1010101 2
0(
1#
1*
1)
1$
1!
b101010 .
b1110111111 0
b10101010 /
b110111111 -
b110111111 4
1+
#1700
0+
#1705
0"
0!
b1110111100 0
b1010100 1
b1010100 2
b101011 .
b110111100 -
b110111100 4
b10101011 /
1+
#1710
0+
#1715
b1010011 1
b1010011 2
0$
b101100 .
b1110111000 0
b10101100 /
b110111000 -
b110111000 4
1+
#1720
0+
#1725
0)
1$
1!
b1110110101 0
b1010010 1
b1010010 2
b101101 .
b110110101 -
b110110101 4
b10101101 /
1+
#1730
0+
#1735
b1010001 1
b1010001 2
0$
1"
0!
b101110 .
b1110110010 0
b10101110 /
b110110010 -
b110110010 4
1+
#1740
0+
#1745
0*
1)
1$
1!
b1110101111 0
b1010000 1
b1010000 2
b101111 .
b110101111 -
b110101111 4
b10101111 /
1+
#1750
0+
#1755
b1001111 1
b1001111 2
0$
b110000 .
b1110101011 0
b10110000 /
b110101011 -
b110101011 4
1+
#1760
0+
#1765
0"
0!
b1110101000 0
b1001110 1
b1001110 2
b110001 .
b110101000 -
b110101000 4
b10110001 /
1+
#1770
0+
#1775
b1001101 1
b1001101 2
0)
1$
b110010 .
b1110100100 0
b10110010 /
b110100100 -
b110100100 4
1+
#1780
0+
#1785
0$
b1110100000 0
b1001100 1
b1001100 2
b110011 .
b110100000 -
b110100000 4
b10110011 /
1+
#1790
0+
#1795
b1001011 1
b1001011 2
0#
1*
1)
1$
1!
b110100 .
b1110011101 0
b10110100 /
b110011101 -
b110011101 4
1+
#1800
0+
#1805
0$
b1110011001 0
b1001010 1
b1001010 2
b110101 .
b110011001 -
b110011001 4
b10110101 /
1+
#1810
0+
#1815
b1001001 1
b1001001 2
0)
1$
b110110 .
b1110010101 0
b10110110 /
b110010101 -
b110010101 4
1+
#1820
0+
#1825
0$
b1110010001 0
b1001000 1
b1001000 2
b110111 .
b110010001 -
b110010001 4
b10110111 /
1+
#1830
0+
#1835
b1000111 1
b1000111 2
0*
1)
1$
b111000 .
b1110001101 0
b10111000 /
b110001101 -
b110001101 4
1+
#1840
0+
#1845
0$
b1110001001 0
b1000110 1
b1000110 2
b111001 .
b110001001 -
b110001001 4
b10111001 /
1+
#1850
0+
