MP3/memory_quarter.sv
module memory_quarter #(
    parameter INIT_FILE = ""
)(
    input  logic       clk,
    input  logic [6:0] read_address, // 7-bit address (0 to 127)
    output logic [8:0] read_data     // 9-bit sample
);

    // Declare memory array for storing 128 9-bit samples of the first quarter cycle
    logic [8:0] sample_memory [0:127];

    // Load samples from INIT_FILE if provided
    initial if (INIT_FILE != "") begin
        $readmemh(INIT_FILE, sample_memory);
    end

    // Synchronous read from the memory array
    always_ff @(posedge clk) begin
        read_data <= sample_memory[read_address];
    end

endmodule

MP3/sine.sv
`include "memory_quarter.sv"  // Use the modified quarter-cycle memory module

module top(
    input  logic clk, 
    output logic _9b,    // D0
    output logic _6a,    // D1
    output logic _4a,    // D2
    output logic _2a,    // D3
    output logic _0a,    // D4
    output logic _5a,    // D5
    output logic _3b,    // D6
    output logic _49a,   // D7
    output logic _45a,   // D8
    output logic _48b    // D9
);

    // Helper function to extract the lower 7 bits without using a constant select.
    function automatic logic [6:0] lower7(input logic [8:0] x);
        lower7 = x - ((x >> 7) << 7);
    endfunction

    // 9-bit counter for 512 sample positions (0 to 511)
    logic [8:0] counter = 0;
    always_ff @(posedge clk) begin
        counter <= counter + 1;
    end

    // Determine which quarter of the cycle and compute quarter address and sign
    logic [6:0] quarter_address;
    logic       sign;
    
    always_comb begin
        if (counter < 9'd128) begin
            // Quarter 1: 0 to 127
            quarter_address = lower7(counter);  // Extract lower 7 bits
            sign = 1'b0;
        end else if (counter < 9'd256) begin
            // Quarter 2: 128 to 255
            quarter_address = 7'd127 - (counter - 9'd128);
            sign = 1'b0;
        end else if (counter < 9'd384) begin
            // Quarter 3: 256 to 383
            quarter_address = counter - 9'd256; // yields 0 to 127
            sign = 1'b1;
        end else begin
            // Quarter 4: 384 to 511
            quarter_address = 7'd127 - (counter - 9'd384);
            sign = 1'b1;
        end
    end

    // Quarter-cycle memory outputs a 9-bit magnitude sample
    logic [8:0] quarter_data;
    memory_quarter #(
        .INIT_FILE("sine_quarter.txt")
    ) u1 (
        .clk(clk),
        .read_address(quarter_address),
        .read_data(quarter_data)
    );

    // Combine sign and magnitude to form a 10-bit sample output.
    // (Assuming a simple sign/magnitude representation.)
    logic [9:0] data;
    assign data = {sign, quarter_data};

    // Map the 10-bit data to the DAC outputs (order may reflect wiring requirements)
    assign {_48b, _45a, _49a, _3b, _5a, _0a, _2a, _4a, _6a, _9b} = data;

endmodule

MP3/sine_tb.sv
`timescale 1ns/1ps
`include "sine.sv"

module tb_top;
    // Clock signal
    logic clk;

    // DAC output wires
    logic _9b;
    logic _6a;
    logic _4a;
    logic _2a;
    logic _0a;
    logic _5a;
    logic _3b;
    logic _49a;
    logic _45a;
    logic _48b;

    // Instantiate the top-level module
    top uut (
        .clk(clk),
        ._9b(_9b),
        ._6a(_6a),
        ._4a(_4a),
        ._2a(_2a),
        ._0a(_0a),
        ._5a(_5a),
        ._3b(_3b),
        ._49a(_49a),
        ._45a(_45a),
        ._48b(_48b)
    );

    // Generate a clock with a 10ns period (100MHz)
    initial begin
        clk = 0;
        forever #5 clk = ~clk;
    end

    // Dump waveforms and end simulation after a full cycle plus margin
    initial begin
        $dumpfile("tb_top.vcd");  // VCD file for viewing waveforms in gtkwave
        $dumpvars(0, tb_top);
        // Run simulation for 6000ns, which covers more than one full cycle (5120ns for one cycle)
        #6000;
        $finish;
    end
endmodule

MP3/tb_top.vcd
$date
	Tue Mar 11 14:25:28 2025
$end
$version
	Icarus Verilog
$end
$timescale
	1ps
$end
$scope module tb_top $end
$var wire 1 ! _9b $end
$var wire 1 " _6a $end
$var wire 1 # _5a $end
$var wire 1 $ _4a $end
$var wire 1 % _49a $end
$var wire 1 & _48b $end
$var wire 1 ' _45a $end
$var wire 1 ( _3b $end
$var wire 1 ) _2a $end
$var wire 1 * _0a $end
$var reg 1 + clk $end
$scope module uut $end
$var wire 1 + clk $end
$var wire 9 , quarter_data [8:0] $end
$var wire 10 - data [9:0] $end
$var wire 1 ! _9b $end
$var wire 1 " _6a $end
$var wire 1 # _5a $end
$var wire 1 $ _4a $end
$var wire 1 % _49a $end
$var wire 1 & _48b $end
$var wire 1 ' _45a $end
$var wire 1 ( _3b $end
$var wire 1 ) _2a $end
$var wire 1 * _0a $end
$var reg 9 . counter [8:0] $end
$var reg 7 / quarter_address [6:0] $end
$var reg 1 0 sign $end
$scope function lower7 $end
$upscope $end
$scope module u1 $end
$var wire 1 + clk $end
$var wire 7 1 read_address [6:0] $end
$var parameter 128 2 INIT_FILE $end
$var reg 9 3 read_data [8:0] $end
$upscope $end
$upscope $end
$upscope $end
$enddefinitions $end
$comment Show the parameter values. $end
$dumpall
b1110011011010010110111001100101010111110111000101110101011000010111001001110100011001010111001000101110011101000111100001110100 2
$end
#0
$dumpvars
bx 3
b0 1
00
b0 /
b0 .
b0xxxxxxxxx -
bx ,
0+
x*
x)
x(
x'
0&
x%
x$
x#
x"
x!
$end
#5000
0'
0%
0(
0#
0*
0)
0$
0"
0!
b0 -
b1 /
b1 1
b0 ,
b0 3
b1 .
1+
#10000
0+
#15000
1$
1"
b10 /
b10 1
b110 -
b10 .
b110 ,
b110 3
1+
#20000
0+
#25000
1)
0"
1!
b1101 -
b11 /
b11 1
b1101 ,
b1101 3
b11 .
1+
#30000
0+
#35000
1*
0)
0$
1"
b100 /
b100 1
b10011 -
b100 .
b10011 ,
b10011 3
1+
#40000
0+
#45000
1)
0"
b11001 -
b101 /
b101 1
b11001 ,
b11001 3
b101 .
1+
#50000
0+
#55000
1#
0*
0)
0!
b110 /
b110 1
b100000 -
b110 .
b100000 ,
b100000 3
1+
#60000
0+
#65000
1$
1"
b100110 -
b111 /
b111 1
b100110 ,
b100110 3
b111 .
1+
#70000
0+
#75000
1)
0"
b1000 /
b1000 1
b101100 -
b1000 .
b101100 ,
b101100 3
1+
#80000
0+
#85000
1*
0)
0$
1"
b110010 -
b1001 /
b1001 1
b110010 ,
b110010 3
b1001 .
1+
#90000
0+
#95000
1)
0"
1!
b1010 /
b1010 1
b111001 -
b1010 .
b111001 ,
b111001 3
1+
#100000
0+
#105000
1$
1"
b111111 -
b1011 /
b1011 1
b111111 ,
b111111 3
b1011 .
1+
#110000
0+
#115000
1(
0#
0*
0)
0"
b1100 /
b1100 1
b1000101 -
b1100 .
b1000101 ,
b1000101 3
1+
#120000
0+
#125000
1)
0!
b1001100 -
b1101 /
b1101 1
b1001100 ,
b1001100 3
b1101 .
1+
#130000
0+
#135000
1*
0)
0$
1"
b1110 /
b1110 1
b1010010 -
b1110 .
b1010010 ,
b1010010 3
1+
#140000
0+
#145000
1)
0"
b1011000 -
b1111 /
b1111 1
b1011000 ,
b1011000 3
b1111 .
1+
#150000
0+
#155000
1$
1"
b10000 /
b10000 1
b1011110 -
b10000 .
b1011110 ,
b1011110 3
1+
#160000
0+
#165000
1#
0*
0)
0"
b1100100 -
b10001 /
b10001 1
b1100100 ,
b1100100 3
b10001 .
1+
#170000
0+
#175000
1)
0$
1"
1!
b10010 /
b10010 1
b1101011 -
b10010 .
b1101011 ,
b1101011 3
1+
#180000
0+
#185000
1*
0)
0"
b1110001 -
b10011 /
b10011 1
b1110001 ,
b1110001 3
b10011 .
1+
#190000
0+
#195000
1$
1"
b10100 /
b10100 1
b1110111 -
b10100 .
b1110111 ,
b1110111 3
1+
#200000
0+
#205000
1)
0"
b1111101 -
b10101 /
b10101 1
b1111101 ,
b1111101 3
b10101 .
1+
#210000
0+
#215000
1%
0(
0#
0*
0)
0$
1"
b10110 /
b10110 1
b10000011 -
b10110 .
b10000011 ,
b10000011 3
1+
#220000
0+
#225000
1)
0"
b10001001 -
b10111 /
b10111 1
b10001001 ,
b10001001 3
b10111 .
1+
#230000
0+
#235000
1$
1"
b11000 /
b11000 1
b10001111 -
b11000 .
b10001111 ,
b10001111 3
1+
#240000
0+
#245000
1*
0)
0"
b10010101 -
b11001 /
b11001 1
b10010101 ,
b10010101 3
b11001 .
1+
#250000
0+
#255000
1)
0!
b11010 /
b11010 1
b10011100 -
b11010 .
b10011100 ,
b10011100 3
1+
#260000
0+
#265000
1#
0*
0)
0$
1"
b10100010 -
b11011 /
b11011 1
b10100010 ,
b10100010 3
b11011 .
1+
#270000
0+
#275000
1$
1!
b11100 /
b11100 1
b10100111 -
b11100 .
b10100111 ,
b10100111 3
1+
#280000
0+
#285000
1)
0"
b10101101 -
b11101 /
b11101 1
b10101101 ,
b10101101 3
b11101 .
1+
#290000
0+
#295000
1*
0)
0$
1"
b11110 /
b11110 1
b10110011 -
b11110 .
b10110011 ,
b10110011 3
1+
#300000
0+
#305000
1)
0"
b10111001 -
b11111 /
b11111 1
b10111001 ,
b10111001 3
b11111 .
1+
#310000
0+
#315000
1$
1"
b100000 /
b100000 1
b10111111 -
b100000 .
b10111111 ,
b10111111 3
1+
#320000
0+
#325000
1(
0#
0*
0)
0"
b11000101 -
b100001 /
b100001 1
b11000101 ,
b11000101 3
b100001 .
1+
#330000
0+
#335000
1)
0$
1"
b100010 /
b100010 1
b11001011 -
b100010 .
b11001011 ,
b11001011 3
1+
#340000
0+
#345000
1*
0)
0"
b11010001 -
b100011 /
b100011 1
b11010001 ,
b11010001 3
b100011 .
1+
#350000
0+
#355000
1$
1"
0!
b100100 /
b100100 1
b11010110 -
b100100 .
b11010110 ,
b11010110 3
1+
#360000
0+
#365000
1)
0"
b11011100 -
b100101 /
b100101 1
b11011100 ,
b11011100 3
b100101 .
1+
#370000
0+
#375000
1#
0*
0)
0$
1"
b100110 /
b100110 1
b11100010 -
b100110 .
b11100010 ,
b11100010 3
1+
#380000
0+
#385000
1$
1!
b11100111 -
b100111 /
b100111 1
b11100111 ,
b11100111 3
b100111 .
1+
#390000
0+
#395000
1)
0"
b101000 /
b101000 1
b11101101 -
b101000 .
b11101101 ,
b11101101 3
1+
#400000
0+
#405000
1*
0)
0$
1"
b11110011 -
b101001 /
b101001 1
b11110011 ,
b11110011 3
b101001 .
1+
#410000
0+
#415000
1)
0"
0!
b101010 /
b101010 1
b11111000 -
b101010 .
b11111000 ,
b11111000 3
1+
#420000
0+
#425000
1$
1"
b11111110 -
b101011 /
b101011 1
b11111110 ,
b11111110 3
b101011 .
1+
#430000
0+
#435000
1'
0%
0(
0#
0*
0)
0$
1!
b101100 /
b101100 1
b100000011 -
b101100 .
b100000011 ,
b100000011 3
1+
#440000
0+
#445000
1)
0"
b100001001 -
b101101 /
b101101 1
b100001001 ,
b100001001 3
b101101 .
1+
#450000
0+
#455000
1$
1"
0!
b101110 /
b101110 1
b100001110 -
b101110 .
b100001110 ,
b100001110 3
1+
#460000
0+
#465000
1*
0)
0$
1!
b100010011 -
b101111 /
b101111 1
b100010011 ,
b100010011 3
b101111 .
1+
#470000
0+
#475000
1)
0"
b110000 /
b110000 1
b100011001 -
b110000 .
b100011001 ,
b100011001 3
1+
#480000
0+
#485000
1$
1"
0!
b100011110 -
b110001 /
b110001 1
b100011110 ,
b100011110 3
b110001 .
1+
#490000
0+
#495000
1#
0*
0)
0$
1!
b110010 /
b110010 1
b100100011 -
b110010 .
b100100011 ,
b100100011 3
1+
#500000
0+
#505000
1)
0"
0!
b100101000 -
b110011 /
b110011 1
b100101000 ,
b100101000 3
b110011 .
1+
#510000
0+
#515000
1$
1!
b110100 /
b110100 1
b100101101 -
b110100 .
b100101101 ,
b100101101 3
1+
#520000
0+
#525000
1*
0)
0$
1"
0!
b100110010 -
b110101 /
b110101 1
b100110010 ,
b100110010 3
b110101 .
1+
#530000
0+
#535000
1$
1!
b110110 /
b110110 1
b100110111 -
b110110 .
b100110111 ,
b100110111 3
1+
#540000
0+
#545000
1)
0"
0!
b100111100 -
b110111 /
b110111 1
b100111100 ,
b100111100 3
b110111 .
1+
#550000
0+
#555000
1(
0#
0*
0)
0$
1!
b111000 /
b111000 1
b101000001 -
b111000 .
b101000001 ,
b101000001 3
1+
#560000
0+
#565000
1$
1"
0!
b101000110 -
b111001 /
b111001 1
b101000110 ,
b101000110 3
b111001 .
1+
#570000
0+
#575000
1)
0$
1!
b111010 /
b111010 1
b101001011 -
b111010 .
b101001011 ,
b101001011 3
1+
#580000
0+
#585000
1*
0)
0"
0!
b101010000 -
b111011 /
b111011 1
b101010000 ,
b101010000 3
b111011 .
1+
#590000
0+
#595000
1$
1!
b111100 /
b111100 1
b101010101 -
b111100 .
b101010101 ,
b101010101 3
1+
#600000
0+
#605000
1)
0$
b101011001 -
b111101 /
b111101 1
b101011001 ,
b101011001 3
b111101 .
1+
#610000
0+
#615000
1$
1"
0!
b111110 /
b111110 1
b101011110 -
b111110 .
b101011110 ,
b101011110 3
1+
#620000
0+
#625000
1#
0*
0)
0$
1!
b101100011 -
b111111 /
b111111 1
b101100011 ,
b101100011 3
b111111 .
1+
#630000
0+
#635000
1$
b1000000 /
b1000000 1
b101100111 -
b1000000 .
b101100111 ,
b101100111 3
1+
#640000
0+
#645000
1)
0"
0!
b101101100 -
b1000001 /
b1000001 1
b101101100 ,
b101101100 3
b1000001 .
1+
#650000
0+
#655000
1*
0)
0$
b1000010 /
b1000010 1
b101110000 -
b1000010 .
b101110000 ,
b101110000 3
1+
#660000
0+
#665000
1$
b101110100 -
b1000011 /
b1000011 1
b101110100 ,
b101110100 3
b1000011 .
1+
#670000
0+
#675000
1)
0$
1!
b1000100 /
b1000100 1
b101111001 -
b1000100 .
b101111001 ,
b101111001 3
1+
#680000
0+
#685000
1$
b101111101 -
b1000101 /
b1000101 1
b101111101 ,
b101111101 3
b1000101 .
1+
#690000
0+
#695000
1%
0(
0#
0*
0)
0$
b1000110 /
b1000110 1
b110000001 -
b1000110 .
b110000001 ,
b110000001 3
1+
#700000
0+
#705000
1$
b110000101 -
b1000111 /
b1000111 1
b110000101 ,
b110000101 3
b1000111 .
1+
#710000
0+
#715000
1)
0$
b1001000 /
b1001000 1
b110001001 -
b1001000 .
b110001001 ,
b110001001 3
1+
#720000
0+
#725000
1$
b110001101 -
b1001001 /
b1001001 1
b110001101 ,
b110001101 3
b1001001 .
1+
#730000
0+
#735000
1*
0)
0$
b1001010 /
b1001010 1
b110010001 -
b1001010 .
b110010001 ,
b110010001 3
1+
#740000
0+
#745000
1$
b110010101 -
b1001011 /
b1001011 1
b110010101 ,
b110010101 3
b1001011 .
1+
#750000
0+
#755000
1)
0$
b1001100 /
b1001100 1
b110011001 -
b1001100 .
b110011001 ,
b110011001 3
1+
#760000
0+
#765000
1$
b110011101 -
b1001101 /
b1001101 1
b110011101 ,
b110011101 3
b1001101 .
1+
#770000
0+
#775000
1#
0*
0)
0$
0!
b1001110 /
b1001110 1
b110100000 -
b1001110 .
b110100000 ,
b110100000 3
1+
#780000
0+
#785000
1$
b110100100 -
b1001111 /
b1001111 1
b110100100 ,
b110100100 3
b1001111 .
1+
#790000
0+
#795000
1)
0$
b1010000 /
b1010000 1
b110101000 -
b1010000 .
b110101000 ,
b110101000 3
1+
#800000
0+
#805000
1"
1!
b110101011 -
b1010001 /
b1010001 1
b110101011 ,
b110101011 3
b1010001 .
1+
#810000
0+
#815000
1$
b1010010 /
b1010010 1
b110101111 -
b1010010 .
b110101111 ,
b110101111 3
1+
#820000
0+
#825000
1*
0)
0$
0!
b110110010 -
b1010011 /
b1010011 1
b110110010 ,
b110110010 3
b1010011 .
1+
#830000
0+
#835000
1$
0"
1!
b1010100 /
b1010100 1
b110110101 -
b1010100 .
b110110101 ,
b110110101 3
1+
#840000
0+
#845000
1)
0$
0!
b110111000 -
b1010101 /
b1010101 1
b110111000 ,
b110111000 3
b1010101 .
1+
#850000
0+
#855000
1$
b1010110 /
b1010110 1
b110111100 -
b1010110 .
b110111100 ,
b110111100 3
1+
#860000
0+
#865000
1"
1!
b110111111 -
b1010111 /
b1010111 1
b110111111 ,
b110111111 3
b1010111 .
1+
#870000
0+
#875000
1(
0#
0*
0)
0$
0!
b1011000 /
b1011000 1
b111000010 -
b1011000 .
b111000010 ,
b111000010 3
1+
#880000
0+
#885000
1$
0"
1!
b111000101 -
b1011001 /
b1011001 1
b111000101 ,
b111000101 3
b1011001 .
1+
#890000
0+
#895000
1)
0$
0!
b1011010 /
b1011010 1
b111001000 -
b1011010 .
b111001000 ,
b111001000 3
1+
#900000
0+
#905000
1"
b111001010 -
b1011011 /
b1011011 1
b111001010 ,
b111001010 3
b1011011 .
1+
#910000
0+
#915000
1$
0"
1!
b1011100 /
b1011100 1
b111001101 -
b1011100 .
b111001101 ,
b111001101 3
1+
#920000
0+
#925000
1*
0)
0$
0!
b111010000 -
b1011101 /
b1011101 1
b111010000 ,
b111010000 3
b1011101 .
1+
#930000
0+
#935000
1"
b1011110 /
b1011110 1
b111010010 -
b1011110 .
b111010010 ,
b111010010 3
1+
#940000
0+
#945000
1$
0"
1!
b111010101 -
b1011111 /
b1011111 1
b111010101 ,
b111010101 3
b1011111 .
1+
#950000
0+
#955000
1"
b1100000 /
b1100000 1
b111010111 -
b1100000 .
b111010111 ,
b111010111 3
1+
#960000
0+
#965000
1)
0$
0!
b111011010 -
b1100001 /
b1100001 1
b111011010 ,
b111011010 3
b1100001 .
1+
#970000
0+
#975000
1$
0"
b1100010 /
b1100010 1
b111011100 -
b1100010 .
b111011100 ,
b111011100 3
1+
#980000
0+
#985000
1"
b111011110 -
b1100011 /
b1100011 1
b111011110 ,
b111011110 3
b1100011 .
1+
#990000
0+
#995000
1#
0*
0)
0$
0"
1!
b1100100 /
b1100100 1
b111100001 -
b1100100 .
b111100001 ,
b111100001 3
1+
#1000000
0+
#1005000
1"
b111100011 -
b1100101 /
b1100101 1
b111100011 ,
b111100011 3
b1100101 .
1+
#1010000
0+
#1015000
1$
0"
b1100110 /
b1100110 1
b111100101 -
b1100110 .
b111100101 ,
b111100101 3
1+
#1020000
0+
#1025000
1"
b111100111 -
b1100111 /
b1100111 1
b111100111 ,
b111100111 3
b1100111 .
1+
#1030000
0+
#1035000
1)
0$
0"
b1101000 /
b1101000 1
b111101001 -
b1101000 .
b111101001 ,
b111101001 3
1+
#1040000
0+
#1045000
1"
0!
b111101010 -
b1101001 /
b1101001 1
b111101010 ,
b111101010 3
b1101001 .
1+
#1050000
0+
#1055000
1$
0"
b1101010 /
b1101010 1
b111101100 -
b1101010 .
b111101100 ,
b111101100 3
1+
#1060000
0+
#1065000
1"
b111101110 -
b1101011 /
b1101011 1
b111101110 ,
b111101110 3
b1101011 .
1+
#1070000
0+
#1075000
1!
b1101100 /
b1101100 1
b111101111 -
b1101100 .
b111101111 ,
b111101111 3
1+
#1080000
0+
#1085000
1*
0)
0$
0"
b111110001 -
b1101101 /
b1101101 1
b111110001 ,
b111110001 3
b1101101 .
1+
#1090000
0+
#1095000
1"
0!
b1101110 /
b1101110 1
b111110010 -
b1101110 .
b111110010 ,
b111110010 3
1+
#1100000
0+
#1105000
1$
0"
b111110100 -
b1101111 /
b1101111 1
b111110100 ,
b111110100 3
b1101111 .
1+
#1110000
0+
#1115000
1!
b1110000 /
b1110000 1
b111110101 -
b1110000 .
b111110101 ,
b111110101 3
1+
#1120000
0+
#1125000
1"
0!
b111110110 -
b1110001 /
b1110001 1
b111110110 ,
b111110110 3
b1110001 .
1+
#1130000
0+
#1135000
1!
b1110010 /
b1110010 1
b111110111 -
b1110010 .
b111110111 ,
b111110111 3
1+
#1140000
0+
#1145000
1)
0$
0"
0!
b111111000 -
b1110011 /
b1110011 1
b111111000 ,
b111111000 3
b1110011 .
1+
#1150000
0+
#1155000
1!
b1110100 /
b1110100 1
b111111001 -
b1110100 .
b111111001 ,
b111111001 3
1+
#1160000
0+
#1165000
1"
0!
b111111010 -
b1110101 /
b1110101 1
b111111010 ,
b111111010 3
b1110101 .
1+
#1170000
0+
#1175000
1!
b1110110 /
b1110110 1
b111111011 -
b1110110 .
b111111011 ,
b111111011 3
1+
#1180000
0+
#1185000
1$
0"
0!
b111111100 -
b1110111 /
b1110111 1
b111111100 ,
b111111100 3
b1110111 .
1+
#1190000
0+
#1195000
1!
b1111000 /
b1111000 1
b111111101 -
b1111000 .
b111111101 ,
b111111101 3
1+
#1200000
0+
#1205000
b1111001 /
b1111001 1
b1111001 .
1+
#1210000
0+
#1215000
1"
0!
b1111010 /
b1111010 1
b111111110 -
b1111010 .
b111111110 ,
b111111110 3
1+
#1220000
0+
#1225000
b1111011 /
b1111011 1
b1111011 .
1+
#1230000
0+
#1235000
b1111100 /
b1111100 1
b1111100 .
1+
#1240000
0+
#1245000
1!
b111111111 -
b1111101 /
b1111101 1
b111111111 ,
b111111111 3
b1111101 .
1+
#1250000
0+
#1255000
b1111110 /
b1111110 1
b1111110 .
1+
#1260000
0+
#1265000
b1111111 /
b1111111 1
b1111111 .
1+
#1270000
0+
#1275000
b10000000 .
1+
#1280000
0+
#1285000
b1111110 /
b1111110 1
b10000001 .
1+
#1290000
0+
#1295000
b1111101 /
b1111101 1
b10000010 .
1+
#1300000
0+
#1305000
b1111100 /
b1111100 1
b10000011 .
1+
#1310000
0+
#1315000
b1111011 /
b1111011 1
b10000100 .
1+
#1320000
0+
#1325000
0!
b111111110 -
b1111010 /
b1111010 1
b111111110 ,
b111111110 3
b10000101 .
1+
#1330000
0+
#1335000
b1111001 /
b1111001 1
b10000110 .
1+
#1340000
0+
#1345000
b1111000 /
b1111000 1
b10000111 .
1+
#1350000
0+
#1355000
0"
1!
b1110111 /
b1110111 1
b111111101 -
b10001000 .
b111111101 ,
b111111101 3
1+
#1360000
0+
#1365000
b1110110 /
b1110110 1
b10001001 .
1+
#1370000
0+
#1375000
0!
b1110101 /
b1110101 1
b111111100 -
b10001010 .
b111111100 ,
b111111100 3
1+
#1380000
0+
#1385000
0$
1"
1!
b111111011 -
b1110100 /
b1110100 1
b111111011 ,
b111111011 3
b10001011 .
1+
#1390000
0+
#1395000
0!
b1110011 /
b1110011 1
b111111010 -
b10001100 .
b111111010 ,
b111111010 3
1+
#1400000
0+
#1405000
0"
1!
b111111001 -
b1110010 /
b1110010 1
b111111001 ,
b111111001 3
b10001101 .
1+
#1410000
0+
#1415000
0!
b1110001 /
b1110001 1
b111111000 -
b10001110 .
b111111000 ,
b111111000 3
1+
#1420000
0+
#1425000
0)
1$
1"
1!
b111110111 -
b1110000 /
b1110000 1
b111110111 ,
b111110111 3
b10001111 .
1+
#1430000
0+
#1435000
0!
b1101111 /
b1101111 1
b111110110 -
b10010000 .
b111110110 ,
b111110110 3
1+
#1440000
0+
#1445000
0"
1!
b111110101 -
b1101110 /
b1101110 1
b111110101 ,
b111110101 3
b10010001 .
1+
#1450000
0+
#1455000
0!
b1101101 /
b1101101 1
b111110100 -
b10010010 .
b111110100 ,
b111110100 3
1+
#1460000
0+
#1465000
0$
1"
b111110010 -
b1101100 /
b1101100 1
b111110010 ,
b111110010 3
b10010011 .
1+
#1470000
0+
#1475000
0"
1!
b1101011 /
b1101011 1
b111110001 -
b10010100 .
b111110001 ,
b111110001 3
1+
#1480000
0+
#1485000
0*
1)
1$
1"
b111101111 -
b1101010 /
b1101010 1
b111101111 ,
b111101111 3
b10010101 .
1+
#1490000
0+
#1495000
0!
b1101001 /
b1101001 1
b111101110 -
b10010110 .
b111101110 ,
b111101110 3
1+
#1500000
0+
#1505000
0"
b111101100 -
b1101000 /
b1101000 1
b111101100 ,
b111101100 3
b10010111 .
1+
#1510000
0+
#1515000
0$
1"
b1100111 /
b1100111 1
b111101010 -
b10011000 .
b111101010 ,
b111101010 3
1+
#1520000
0+
#1525000
0"
1!
b111101001 -
b1100110 /
b1100110 1
b111101001 ,
b111101001 3
b10011001 .
1+
#1530000
0+
#1535000
0)
1$
1"
b1100101 /
b1100101 1
b111100111 -
b10011010 .
b111100111 ,
b111100111 3
1+
#1540000
0+
#1545000
0"
b111100101 -
b1100100 /
b1100100 1
b111100101 ,
b111100101 3
b10011011 .
1+
#1550000
0+
#1555000
0$
1"
b1100011 /
b1100011 1
b111100011 -
b10011100 .
b111100011 ,
b111100011 3
1+
#1560000
0+
#1565000
0"
b111100001 -
b1100010 /
b1100010 1
b111100001 ,
b111100001 3
b10011101 .
1+
#1570000
0+
#1575000
0#
1*
1)
1$
1"
0!
b1100001 /
b1100001 1
b111011110 -
b10011110 .
b111011110 ,
b111011110 3
1+
#1580000
0+
#1585000
0"
b111011100 -
b1100000 /
b1100000 1
b111011100 ,
b111011100 3
b10011111 .
1+
#1590000
0+
#1595000
0$
1"
b1011111 /
b1011111 1
b111011010 -
b10100000 .
b111011010 ,
b111011010 3
1+
#1600000
0+
#1605000
0)
1$
1!
b111010111 -
b1011110 /
b1011110 1
b111010111 ,
b111010111 3
b10100001 .
1+
#1610000
0+
#1615000
0"
b1011101 /
b1011101 1
b111010101 -
b10100010 .
b111010101 ,
b111010101 3
1+
#1620000
0+
#1625000
0$
1"
0!
b111010010 -
b1011100 /
b1011100 1
b111010010 ,
b111010010 3
b10100011 .
1+
#1630000
0+
#1635000
0"
b1011011 /
b1011011 1
b111010000 -
b10100100 .
b111010000 ,
b111010000 3
1+
#1640000
0+
#1645000
0*
1)
1$
1!
b111001101 -
b1011010 /
b1011010 1
b111001101 ,
b111001101 3
b10100101 .
1+
#1650000
0+
#1655000
0$
1"
0!
b1011001 /
b1011001 1
b111001010 -
b10100110 .
b111001010 ,
b111001010 3
1+
#1660000
0+
#1665000
0"
b111001000 -
b1011000 /
b1011000 1
b111001000 ,
b111001000 3
b10100111 .
1+
#1670000
0+
#1675000
0)
1$
1!
b1010111 /
b1010111 1
b111000101 -
b10101000 .
b111000101 ,
b111000101 3
1+
#1680000
0+
#1685000
0$
1"
0!
b111000010 -
b1010110 /
b1010110 1
b111000010 ,
b111000010 3
b10101001 .
1+
#1690000
0+
#1695000
0(
1#
1*
1)
1$
1!
b1010101 /
b1010101 1
b110111111 -
b10101010 .
b110111111 ,
b110111111 3
1+
#1700000
0+
#1705000
0"
0!
b110111100 -
b1010100 /
b1010100 1
b110111100 ,
b110111100 3
b10101011 .
1+
#1710000
0+
#1715000
0$
b1010011 /
b1010011 1
b110111000 -
b10101100 .
b110111000 ,
b110111000 3
1+
#1720000
0+
#1725000
0)
1$
1!
b110110101 -
b1010010 /
b1010010 1
b110110101 ,
b110110101 3
b10101101 .
1+
#1730000
0+
#1735000
0$
1"
0!
b1010001 /
b1010001 1
b110110010 -
b10101110 .
b110110010 ,
b110110010 3
1+
#1740000
0+
#1745000
0*
1)
1$
1!
b110101111 -
b1010000 /
b1010000 1
b110101111 ,
b110101111 3
b10101111 .
1+
#1750000
0+
#1755000
0$
b1001111 /
b1001111 1
b110101011 -
b10110000 .
b110101011 ,
b110101011 3
1+
#1760000
0+
#1765000
0"
0!
b110101000 -
b1001110 /
b1001110 1
b110101000 ,
b110101000 3
b10110001 .
1+
#1770000
0+
#1775000
0)
1$
b1001101 /
b1001101 1
b110100100 -
b10110010 .
b110100100 ,
b110100100 3
1+
#1780000
0+
#1785000
0$
b110100000 -
b1001100 /
b1001100 1
b110100000 ,
b110100000 3
b10110011 .
1+
#1790000
0+
#1795000
0#
1*
1)
1$
1!
b1001011 /
b1001011 1
b110011101 -
b10110100 .
b110011101 ,
b110011101 3
1+
#1800000
0+
#1805000
0$
b110011001 -
b1001010 /
b1001010 1
b110011001 ,
b110011001 3
b10110101 .
1+
#1810000
0+
#1815000
0)
1$
b1001001 /
b1001001 1
b110010101 -
b10110110 .
b110010101 ,
b110010101 3
1+
#1820000
0+
#1825000
0$
b110010001 -
b1001000 /
b1001000 1
b110010001 ,
b110010001 3
b10110111 .
1+
#1830000
0+
#1835000
0*
1)
1$
b1000111 /
b1000111 1
b110001101 -
b10111000 .
b110001101 ,
b110001101 3
1+
#1840000
0+
#1845000
0$
b110001001 -
b1000110 /
b1000110 1
b110001001 ,
b110001001 3
b10111001 .
1+
#1850000
0+
#1855000
0)
1$
b1000101 /
b1000101 1
b110000101 -
b10111010 .
b110000101 ,
b110000101 3
1+
#1860000
0+
#1865000
0$
b110000001 -
b1000100 /
b1000100 1
b110000001 ,
b110000001 3
b10111011 .
1+
#1870000
0+
#1875000
0%
1(
1#
1*
1)
1$
b1000011 /
b1000011 1
b101111101 -
b10111100 .
b101111101 ,
b101111101 3
1+
#1880000
0+
#1885000
0$
b101111001 -
b1000010 /
b1000010 1
b101111001 ,
b101111001 3
b10111101 .
1+
#1890000
0+
#1895000
0)
1$
0!
b1000001 /
b1000001 1
b101110100 -
b10111110 .
b101110100 ,
b101110100 3
1+
#1900000
0+
#1905000
0$
b101110000 -
b1000000 /
b1000000 1
b101110000 ,
b101110000 3
b10111111 .
1+
#1910000
0+
#1915000
0*
1)
1$
b111111 /
b111111 1
b101101100 -
b11000000 .
b101101100 ,
b101101100 3
1+
#1920000
0+
#1925000
0)
1"
1!
b101100111 -
b111110 /
b111110 1
b101100111 ,
b101100111 3
b11000001 .
1+
#1930000
0+
#1935000
0$
b111101 /
b111101 1
b101100011 -
b11000010 .
b101100011 ,
b101100011 3
1+
#1940000
0+
#1945000
0#
1*
1)
1$
0!
b101011110 -
b111100 /
b111100 1
b101011110 ,
b101011110 3
b11000011 .
1+
#1950000
0+
#1955000
0$
0"
1!
b111011 /
b111011 1
b101011001 -
b11000100 .
b101011001 ,
b101011001 3
1+
#1960000
0+
#1965000
0)
1$
b101010101 -
b111010 /
b111010 1
b101010101 ,
b101010101 3
b11000101 .
1+
#1970000
0+
#1975000
0$
0!
b111001 /
b111001 1
b101010000 -
b11000110 .
b101010000 ,
b101010000 3
1+
#1980000
0+
#1985000
0*
1)
1"
1!
b101001011 -
b111000 /
b111000 1
b101001011 ,
b101001011 3
b11000111 .
1+
#1990000
0+
#1995000
0)
1$
0!
b110111 /
b110111 1
b101000110 -
b11001000 .
b101000110 ,
b101000110 3
1+
#2000000
0+
